README.md
setup.py
init_data/01-欢迎使用SNB.snb
init_data/02-数据分析方法-RFM模型实战.snb
init_data/03-数据分析方法-漏斗分析实战.snb
init_data/04-数据分析方法-留存分析(cohort analysis)实战.snb
init_data/05-机器学习实例-鸢尾花.snb
init_data/06-机器学习实例-泰坦尼克号.snb
init_data/Iris.csv
init_data/__init__.py
init_data/demo.duckdb
init_data/home_page_table.csv
init_data/payment_confirmation_table.csv
init_data/payment_page_table.csv
init_data/search_page_table.csv
init_data/snb_server_db_1.0.sql
init_data/test_titanic.csv
init_data/train_titanic.csv
init_data/user_table.csv
pytransform/__init__.py
pytransform/_pytransform.so
snb_server/ImpExportWS.py
snb_server/__init__.py
snb_server/__main__.py
snb_server/ascii_logo.txt
snb_server/helloworld.py
snb_server/initSnbDB.py
snb_server/smartnotebookapp.py
snb_server.egg-info/PKG-INFO
snb_server.egg-info/SOURCES.txt
snb_server.egg-info/dependency_links.txt
snb_server.egg-info/top_level.txt
snb_server/config/Config.py
snb_server/config/__init__.py
snb_server/config/db_init_script.sql
snb_server/config/email_exec_log.html
snb_server/config/email_invit.html
snb_server/config/email_reg.html
snb_server/config/email_resetpw.html
snb_server/config/template.html
snb_server/services/LoginPageConfHandlers.py
snb_server/services/__init__.py
snb_server/services/permiConfHandlers.py
snb_server/services/base/__init__.py
snb_server/services/base/handlers.py
snb_server/services/base/managers.py
snb_server/services/chatgpt/__init__.py
snb_server/services/chatgpt/handlers.py
snb_server/services/chatgpt/models.py
snb_server/services/datasource/__init__.py
snb_server/services/datasource/handlers.py
snb_server/services/datasource/models.py
snb_server/services/files/__init__.py
snb_server/services/files/handlers.py
snb_server/services/imp_export/__init__.py
snb_server/services/imp_export/imp_export_util.py
snb_server/services/notebook/LowToCodeHandlers.py
snb_server/services/notebook/SNBFileHandlers.py
snb_server/services/notebook/SnbToGrapHandlers.py
snb_server/services/notebook/__init__.py
snb_server/services/notebook/handlers.py
snb_server/services/notebook_obj/SnbIpynbUtil.py
snb_server/services/notebook_obj/__init__.py
