Metadata-Version: 2.1
Name: snb-server
Version: 1.6.6
Summary: smart-notebook server
Home-page: http://smartnotebook.tech/
Author: wang xin yi
Author-email: wangxinyi@smartnotebook.tech
